{
  "ControlStates": {
    "Component1_2": {
      "AllowAccessToGlobals": true,
      "ControlPropertyState": [
        "Fill",
        {
          "AFDDataSourceName": "",
          "AutoRuleBindingEnabled": false,
          "AutoRuleBindingString": "",
          "InvariantPropertyName": "Height",
          "IsLockable": false,
          "NameMapSourceSchema": "?"
        },
        {
          "AFDDataSourceName": "",
          "AutoRuleBindingEnabled": false,
          "AutoRuleBindingString": "",
          "InvariantPropertyName": "Width",
          "IsLockable": false,
          "NameMapSourceSchema": "?"
        },
        "X",
        "Y",
        "ZIndex",
        "Menu",
        {
          "AFDDataSourceName": "",
          "AutoRuleBindingEnabled": false,
          "AutoRuleBindingString": "\"Text\"",
          "InvariantPropertyName": "CurrentScreen",
          "IsLockable": false,
          "NameMapSourceSchema": "?"
        },
        "NavType",
        "IsSubMenuVisible",
        "MaxSubMenu",
        "submenu_inbox"
      ],
      "HasDynamicProperties": false,
      "IsAutoGenerated": false,
      "IsComponentDefinition": false,
      "IsDataControl": false,
      "IsFromScreenLayout": false,
      "IsGroupControl": false,
      "IsLocked": false,
      "LayoutName": "",
      "Metadata": {
        "AllowAccessToGlobals": false,
        "AllowCustomization": true,
        "Description": ""
      },
      "MetaDataIDKey": "",
      "Name": "Component1_2",
      "ParentIndex": 0,
      "PersistMetaDataIDKey": false,
      "Properties": [
        {
          "Category": "Data",
          "PropertyName": "Menu",
          "RuleProviderType": "System"
        },
        {
          "Category": "Data",
          "PropertyName": "CurrentScreen",
          "RuleProviderType": "Unknown"
        },
        {
          "Category": "Data",
          "PropertyName": "NavType",
          "RuleProviderType": "System"
        },
        {
          "Category": "Data",
          "PropertyName": "IsSubMenuVisible",
          "RuleProviderType": "System"
        },
        {
          "Category": "Data",
          "PropertyName": "MaxSubMenu",
          "RuleProviderType": "System"
        },
        {
          "Category": "Data",
          "PropertyName": "submenu_inbox",
          "RuleProviderType": "System"
        },
        {
          "Category": "Design",
          "PropertyName": "Fill",
          "RuleProviderType": "System"
        },
        {
          "Category": "Design",
          "PropertyName": "Height",
          "RuleProviderType": "Unknown"
        },
        {
          "Category": "Design",
          "PropertyName": "Width",
          "RuleProviderType": "Unknown"
        },
        {
          "Category": "Design",
          "PropertyName": "X",
          "RuleProviderType": "Unknown"
        },
        {
          "Category": "Design",
          "PropertyName": "Y",
          "RuleProviderType": "Unknown"
        },
        {
          "Category": "Design",
          "PropertyName": "ZIndex",
          "RuleProviderType": "Unknown"
        }
      ],
      "StyleName": "",
      "Type": "ControlInfo"
    },
    "Inbox": {
      "AllowAccessToGlobals": true,
      "ControlPropertyState": [
        "Fill",
        "ImagePosition",
        "Height",
        "Width",
        "Size",
        "Orientation",
        "LoadingSpinner",
        "LoadingSpinnerColor"
      ],
      "IsAutoGenerated": false,
      "IsComponentDefinition": false,
      "IsDataControl": false,
      "IsFromScreenLayout": false,
      "IsGroupControl": false,
      "IsLocked": false,
      "LayoutName": "",
      "MetaDataIDKey": "",
      "Name": "Inbox",
      "ParentIndex": 0,
      "PersistMetaDataIDKey": false,
      "Properties": [
        {
          "Category": "Design",
          "PropertyName": "Width",
          "RuleProviderType": "Unknown"
        },
        {
          "Category": "Design",
          "PropertyName": "Height",
          "RuleProviderType": "Unknown"
        },
        {
          "Category": "Design",
          "PropertyName": "ImagePosition",
          "RuleProviderType": "Unknown"
        },
        {
          "Category": "Design",
          "PropertyName": "Fill",
          "RuleProviderType": "Unknown"
        },
        {
          "Category": "Design",
          "PropertyName": "LoadingSpinner",
          "RuleProviderType": "Unknown"
        },
        {
          "Category": "Design",
          "PropertyName": "LoadingSpinnerColor",
          "RuleProviderType": "Unknown"
        },
        {
          "Category": "Design",
          "PropertyName": "Size",
          "RuleProviderType": "Unknown"
        },
        {
          "Category": "Design",
          "PropertyName": "Orientation",
          "RuleProviderType": "Unknown"
        }
      ],
      "StyleName": "defaultScreenStyle",
      "Type": "ControlInfo"
    },
    "Inbox(com)_1": {
      "AllowAccessToGlobals": true,
      "ControlPropertyState": [
        "Fill",
        {
          "AFDDataSourceName": "",
          "AutoRuleBindingEnabled": false,
          "AutoRuleBindingString": "",
          "InvariantPropertyName": "Height",
          "IsLockable": false,
          "NameMapSourceSchema": "?"
        },
        {
          "AFDDataSourceName": "",
          "AutoRuleBindingEnabled": false,
          "AutoRuleBindingString": "",
          "InvariantPropertyName": "Width",
          "IsLockable": false,
          "NameMapSourceSchema": "?"
        },
        "X",
        "Y",
        "ZIndex",
        {
          "AFDDataSourceName": "",
          "AutoRuleBindingEnabled": false,
          "AutoRuleBindingString": "Table({Title:\"All Study\",TargetScreen:App.ActiveScreen})",
          "InvariantPropertyName": "inbox_menu",
          "IsLockable": false,
          "NameMapSourceSchema": "?"
        },
        "Currentscreen"
      ],
      "HasDynamicProperties": false,
      "IsAutoGenerated": false,
      "IsComponentDefinition": false,
      "IsDataControl": false,
      "IsFromScreenLayout": false,
      "IsGroupControl": false,
      "IsLocked": false,
      "LayoutName": "",
      "Metadata": {
        "AllowAccessToGlobals": false,
        "AllowCustomization": true,
        "Description": ""
      },
      "MetaDataIDKey": "",
      "Name": "Inbox(com)_1",
      "ParentIndex": 1,
      "PersistMetaDataIDKey": false,
      "Properties": [
        {
          "Category": "Data",
          "PropertyName": "inbox_menu",
          "RuleProviderType": "Unknown"
        },
        {
          "Category": "Data",
          "PropertyName": "Currentscreen",
          "RuleProviderType": "System"
        },
        {
          "Category": "Design",
          "PropertyName": "ZIndex",
          "RuleProviderType": "Unknown"
        },
        {
          "Category": "Design",
          "PropertyName": "Y",
          "RuleProviderType": "Unknown"
        },
        {
          "Category": "Design",
          "PropertyName": "X",
          "RuleProviderType": "Unknown"
        },
        {
          "Category": "Design",
          "PropertyName": "Width",
          "RuleProviderType": "Unknown"
        },
        {
          "Category": "Design",
          "PropertyName": "Height",
          "RuleProviderType": "Unknown"
        },
        {
          "Category": "Design",
          "PropertyName": "Fill",
          "RuleProviderType": "System"
        }
      ],
      "StyleName": "",
      "Type": "ControlInfo"
    }
  },
  "TopParentName": "Inbox"
}